[{"book": "Book1", "Unlocking Charm": 1, "Apparition": 3, "Leg-Locker Curse": 4, "Curse of the Bogies": 2, "Levitation Charm": 5}, {"book": "Book2", "Apparition": 3, "Disarming Charm": 4, "Wand-Lighting Charm": 1, "Memory Charm": 5, "Tickling Charm": 2}, {"book": "Book3", "Apparition": 4, "Cheering Charm": 3, "Disarming Charm": 1, "Wand-Lighting Charm": 2, "Boggart-Banishing Spell": 5}, {"book": "Book4", "Summoning Charm": 3, "Cruciatus Curse": 2, "Imperius Curse": 4, "Dark Mark": 5, "Stunning Spell": 1}, {"book": "Book5", "Summoning Charm": 4, "Apparition": 5, "Vanishing Spell": 2, "Imperius Curse": 1, "Stunning Spell": 3}, {"book": "Book6", "Water-Making Spell": 3, "Apparition": 5, "Killing Curse": 1, "Imperius Curse": 2, "Dark Mark": 4}, {"book": "Book7", "Summoning Charm": 2, "Apparition": 3, "Killing Curse": 4, "Shield Charm": 1, "Stunning Spell": 5}]